rabbitmq_alphamoon/__init__.py
rabbitmq_alphamoon/connectors.py
rabbitmq_alphamoon/logger.py
rabbitmq_alphamoon/testing.py
rabbitmq_alphamoon-0.8.3.dist-info/LICENSE
rabbitmq_alphamoon-0.8.3.dist-info/METADATA
rabbitmq_alphamoon-0.8.3.dist-info/WHEEL
rabbitmq_alphamoon-0.8.3.dist-info/top_level.txt
rabbitmq_alphamoon-0.8.3.dist-info/RECORD
