Metadata-Version: 2.1
Name: rabbitmq-alphamoon
Version: 0.8.3
Summary: pika-based RabbitMQ connector with built in JSON serialization/deserialization
Home-page: https://gitlab.com/alphamoon/internal_tools/rabbitmq-alphamoon
Author: Piotr Dąbrowski
Author-email: piotr.dabrowski@alphamoon.ai
Maintainer: Piotr Dąbrowski
Maintainer-email: dev@alphamoon.ai
License: MIT
Platform: UNKNOWN
Classifier: Development Status :: 4 - Beta
Classifier: Intended Audience :: Developers
Classifier: Programming Language :: Python
Classifier: Programming Language :: Python :: 3
Classifier: Programming Language :: Python :: 3.8
Classifier: Programming Language :: Python :: Implementation :: PyPy
Classifier: Operating System :: OS Independent
Classifier: License :: OSI Approved :: MIT License
Requires-Python: >=3.8
License-File: LICENSE
Requires-Dist: pika (==1.2.0)
Requires-Dist: psutil (==5.7.3)
